cruisecontrolclient/__init__.py
cruisecontrolclient/client/Endpoint.py
cruisecontrolclient/client/ExecutionContext.py
cruisecontrolclient/client/Query.py
cruisecontrolclient/client/Responder.py
cruisecontrolclient/client/__init__.py
cruisecontrolclient/client/cccli.py
cruisecontrolclient/client/CCParameter/BooleanParameter.py
cruisecontrolclient/client/CCParameter/CommaSeparatedParameter.py
cruisecontrolclient/client/CCParameter/NonNegativeIntegerParameter.py
cruisecontrolclient/client/CCParameter/Parameter.py
cruisecontrolclient/client/CCParameter/PositiveIntegerParameter.py
cruisecontrolclient/client/CCParameter/RegularExpressionParameter.py
cruisecontrolclient/client/CCParameter/SetOfChoicesParameter.py
cruisecontrolclient/client/CCParameter/TimeStampParameter.py
cruisecontrolclient/client/CCParameter/__init__.py
cruisecontrolclient/util/__init__.py
cruisecontrolclient/util/print.py
cruise_control_client-1.1.3.dist-info/METADATA
cruise_control_client-1.1.3.dist-info/WHEEL
cruise_control_client-1.1.3.dist-info/entry_points.txt
cruise_control_client-1.1.3.dist-info/top_level.txt
cruise_control_client-1.1.3.dist-info/RECORD
